safeds_runner/__init__.py
safeds_runner/cli/__init__.py
safeds_runner/cli/_cli.py
safeds_runner/main.py
safeds_runner/memoization/__init__.py
safeds_runner/memoization/_memoization_map.py
safeds_runner/memoization/_memoization_stats.py
safeds_runner/memoization/_memoization_strategies.py
safeds_runner/memoization/_memoization_utils.py
safeds_runner/server/__init__.py
safeds_runner/server/_json_encoder.py
safeds_runner/server/_messages.py
safeds_runner/server/_module_manager.py
safeds_runner/server/_pipeline_manager.py
safeds_runner/server/_process_manager.py
safeds_runner/server/_server.py
safeds_runner/server/main.py
safe_ds_runner-0.20.0.dist-info/LICENSE
safe_ds_runner-0.20.0.dist-info/METADATA
safe_ds_runner-0.20.0.dist-info/WHEEL
safe_ds_runner-0.20.0.dist-info/entry_points.txt
safe_ds_runner-0.20.0.dist-info/RECORD
