Metadata-Version: 2.3
Name: safe-ds-runner
Version: 0.20.0
Summary: Execute Safe-DS programs that were compiled to Python.
License: MIT
Keywords: data-science,machine-learning,usability,learnability
Author: Lars Reimann
Author-email: mail@larsreimann.com
Requires-Python: >=3.12,<3.14
Classifier: License :: OSI Approved :: MIT License
Classifier: Programming Language :: Python :: 3
Classifier: Programming Language :: Python :: 3.12
Classifier: Programming Language :: Python :: 3.13
Requires-Dist: hypercorn (>=0.16,<0.18)
Requires-Dist: psutil (>=5.9.8,<8.0.0)
Requires-Dist: pydantic (>=2.9.2,<3.0.0)
Requires-Dist: quart (>=0.19.4,<0.21.0)
Requires-Dist: safe-ds (>=0.31.0,<0.32.0)
Project-URL: Documentation, https://safe-ds-runner.readthedocs.io
Project-URL: Repository, https://github.com/Safe-DS/Runner
